CHANGES.txt
buildout.cfg
setup.py
bootstrap/bootstrap.py
src/zc/__init__.py
src/zc.recipe.macro.egg-info/PKG-INFO
src/zc.recipe.macro.egg-info/SOURCES.txt
src/zc.recipe.macro.egg-info/dependency_links.txt
src/zc.recipe.macro.egg-info/entry_points.txt
src/zc.recipe.macro.egg-info/namespace_packages.txt
src/zc.recipe.macro.egg-info/not-zip-safe
src/zc.recipe.macro.egg-info/requires.txt
src/zc.recipe.macro.egg-info/top_level.txt
src/zc/recipe/__init__.py
src/zc/recipe/macro/QUICKSTART.txt
src/zc/recipe/macro/README.txt
src/zc/recipe/macro/__init__.py
src/zc/recipe/macro/recipe.py
src/zc/recipe/macro/tests.py