Metadata-Version: 1.0
Name: zc.recipe.macro
Version: 1.2.3
Summary: Macro-recipe for buildout.
Home-page: UNKNOWN
Author: Aaron Lehmann
Author-email: aaron@zope.com
License: ZPL 2.1
Keywords: development build macro
Platform: UNKNOWN
Classifier: Framework :: Buildout
Classifier: Intended Audience :: Developers
Classifier: License :: OSI Approved :: Zope Public License
Classifier: Topic :: Software Development :: Build Tools
Classifier: Topic :: Software Development :: Libraries :: Python Modules
